kithon/__init__.py
kithon/analogs.py
kithon/blocks.py
kithon/commands/__init__.py
kithon/commands/configurator.py
kithon/commands/gen.py
kithon/commands/new.py
kithon/commands/repl.py
kithon/commands/run.py
kithon/commands/watch.py
kithon/contexts.py
kithon/controls.py
kithon/core.py
kithon/expressions.py
kithon/node.py
kithon/side_effects.py
kithon/types.py
translators/c-like/core.tp
translators/c-like/macros.tp
translators/go/core.tp
translators/go/libs/json.tp
translators/go/macros.tp
translators/go/objects/list.tp
translators/go/objects/str.tp
translators/js/core.tp
translators/js/libs/dom.tp
translators/js/libs/json.tp
translators/js/libs/math.tp
translators/js/libs/random.tp
translators/js/libs/react.tp
translators/js/macros.tp
translators/js/meta.tp
translators/js/objects/list.tp
translators/js/objects/str.tp
translators/lua/core.tp
translators/lua/macros.tp
translators/lua/objects/list.tp
translators/lua/tools.tp
translators/python/core.tp
translators/python/libs/math.tp
translators/python/libs/random.tp
translators/python/libs/typing.tp
translators/python/macros.tp
translators/python/objects/str.tp
translators/python/type-inference-rules.tp
kithon-0.6.0.post1.dist-info/LICENSE.txt
kithon-0.6.0.post1.dist-info/METADATA
kithon-0.6.0.post1.dist-info/WHEEL
kithon-0.6.0.post1.dist-info/entry_points.txt
kithon-0.6.0.post1.dist-info/RECORD
