Metadata-Version: 2.1
Name: kithon
Version: 0.6.0.post1
Summary: transpiler python into other languages
Home-page: https://github.com/alploskov/kithon
License: MIT
Author: Aleksey Ploskov
Requires-Python: >=3.9.0,<3.12
Classifier: License :: OSI Approved :: MIT License
Classifier: Programming Language :: Python :: 3
Classifier: Programming Language :: Python :: 3.9
Classifier: Programming Language :: Python :: 3.10
Classifier: Programming Language :: Python :: 3.11
Provides-Extra: add-langs
Provides-Extra: all
Provides-Extra: pyx
Provides-Extra: repl
Provides-Extra: watch
Requires-Dist: Jinja2 (>=2.11.2,<4.0.0)
Requires-Dist: PyYaml (>=5.4.0)
Requires-Dist: coconut (>=1.6.0,<2.0.0) ; extra == "add-langs" or extra == "all"
Requires-Dist: hy (<2.0) ; extra == "add-langs" or extra == "all"
Requires-Dist: packed (>=0.2,<0.3) ; extra == "pyx" or extra == "all"
Requires-Dist: pexpect (>=4.8.0,<5.0.0) ; extra == "repl" or extra == "all"
Requires-Dist: ptpython (>=3.0.20,<4.0.0) ; extra == "repl" or extra == "all"
Requires-Dist: typer (>=0.4.0,<0.5.0)
Requires-Dist: watchdog (>=2.1.7,<3.0.0) ; extra == "watch" or extra == "all"
Project-URL: Repository, https://github.com/alploskov/kithon
